django_user_trace/__init__.py
django_user_trace/apps.py
django_user_trace/asgi.py
django_user_trace/conf.py
django_user_trace/context.py
django_user_trace/contrib/__init__.py
django_user_trace/contrib/celery/__init__.py
django_user_trace/contrib/celery/apps.py
django_user_trace/contrib/celery/signals.py
django_user_trace/log.py
django_user_trace/middleware.py
django_user_trace/py.typed
django_user_trace/signals.py
django_user_trace/utils.py
django_user_trace-2.2.0.dist-info/WHEEL
django_user_trace-2.2.0.dist-info/METADATA
django_user_trace-2.2.0.dist-info/RECORD
