Metadata-Version: 2.4
Name: django-user-trace
Version: 2.2.0
Summary: A Python logging filter for Django user attributes.
Keywords: async,django,logs,logging,middleware,sync,trace,tracing,user,web
Author: Jonathan Hiles
Author-email: Jonathan Hiles <jonathan@hil.es>>
License-Expression: MIT
Classifier: Framework :: Django
Classifier: Framework :: Django :: 5.0
Classifier: Intended Audience :: Developers
Classifier: Operating System :: OS Independent
Classifier: Topic :: Software Development :: Libraries :: Python Modules
Classifier: Typing :: Typed
Requires-Dist: django>=5.0
Requires-Dist: celery>=5.3 ; extra == 'celery'
Requires-Dist: channels>=4.2 ; extra == 'channels'
Requires-Python: >=3.10
Project-URL: Funding, https://github.com/sponsors/axieum
Project-URL: Issue tracker, https://github.com/axieum/django-user-trace/issues
Project-URL: Release notes, https://axieum.github.io/django-user-trace/latest/changelog/
Provides-Extra: celery
Provides-Extra: channels
